git_profile-1.1.3.dist-info/METADATA
git_profile-1.1.3.dist-info/WHEEL
git_profile-1.1.3.dist-info/entry_points.txt
git_profile-1.1.3.dist-info/licenses/LICENSE.txt
git_profile_command/__init__.py
git_profile_command/_vendor/__init__.py
git_profile_command/_vendor/gitconfigparser.py
git_profile_command/py.typed
git_profile-1.1.3.dist-info/RECORD
