Metadata-Version: 2.1
Name: git-profile
Version: 1.1.3
Summary: Easily switch between Git configurations on a per-repository basis.
Author-Email: Niklas Rosenstein <rosensteinniklas@gmail.com>
License: MIT
Project-URL: Repository, https://github.com/NiklasRosenstein/git-profile
Project-URL: Issues, https://github.com/NiklasRosenstein/git-profile/issues
Requires-Python: >=3.8
Requires-Dist: databind>=4.5.2
